minchin/pelican/plugins/autoloader.py
minchin/pelican/plugins/autoloader_tests/__init__.py
minchin/pelican/plugins/autoloader_tests/test_framework.py
minchin/pelican/plugins/autoloader_tests/test_version.py
minchin_pelican_plugins_autoloader-1.2.4.dist-info/licenses/LICENSE.txt
pelican/plugins/autoloader/__init__.py
minchin_pelican_plugins_autoloader-1.2.4.dist-info/METADATA
minchin_pelican_plugins_autoloader-1.2.4.dist-info/WHEEL
minchin_pelican_plugins_autoloader-1.2.4.dist-info/top_level.txt
minchin_pelican_plugins_autoloader-1.2.4.dist-info/RECORD
