Metadata-Version: 2.4
Name: minchin.pelican.plugins.autoloader
Version: 1.2.4
Summary: Pelican plugin, used to auto-load my other plugins.
Author-email: William Minchin <w_minchin@hotmail.com>
Maintainer-email: William Minchin <w_minchin@hotmail.com>
License-Expression: MIT
Project-URL: Bug Tracker, https://github.com/MinchinWeb/minchin.pelican.plugins.autoloader/issues
Project-URL: Repository, https://github.com/MinchinWeb/minchin.pelican.plugins.autoloader
Project-URL: Changelog, https://github.com/minchinweb/minchin.pelican.plugins.autoloader/blob/master/CHANGELOG.rst
Classifier: Development Status :: 5 - Production/Stable
Classifier: Environment :: Console
Classifier: Framework :: Pelican :: Plugins
Classifier: Programming Language :: Python :: 3
Classifier: Programming Language :: Python :: 3.8
Classifier: Programming Language :: Python :: 3.9
Classifier: Programming Language :: Python :: 3.10
Classifier: Programming Language :: Python :: 3.11
Classifier: Programming Language :: Python :: 3.12
Classifier: Programming Language :: Python :: 3.13
Classifier: Programming Language :: Python :: 3.14
Classifier: Programming Language :: Python :: 3 :: Only
Classifier: Natural Language :: English
Classifier: Intended Audience :: Developers
Classifier: Operating System :: OS Independent
Classifier: Topic :: Software Development :: Libraries :: Python Modules
License-File: LICENSE.txt
Requires-Dist: pelican
Requires-Dist: packaging
Provides-Extra: build
Requires-Dist: pip-tools; extra == "build"
Requires-Dist: minchin.releaser>=0.8.2; extra == "build"
Provides-Extra: docs
Provides-Extra: test
Requires-Dist: pytest; extra == "test"
Provides-Extra: dev
Requires-Dist: markdown; extra == "dev"
Requires-Dist: minchin.pelican.plugins.nojekyll; extra == "dev"
Provides-Extra: lint
Requires-Dist: black; extra == "lint"
Requires-Dist: isort; extra == "lint"
Dynamic: license-file
